MANIFEST.in
setup.cfg
setup.py
bootstrap_markdown/__init__.py
bootstrap_markdown/apps.py
bootstrap_markdown/settings.py
bootstrap_markdown/widgets.py
bootstrap_markdown/static/bootstrap_markdown/css/bootstrap-markdown.min.css
bootstrap_markdown/static/bootstrap_markdown/js/bootstrap-markdown.js
bootstrap_markdown/static/bootstrap_markdown/js/markdown.js
bootstrap_markdown/static/bootstrap_markdown/js/to-markdown.js
bootstrap_markdown/static/bootstrap_markdown/locale/bootstrap-markdown.ar.js
bootstrap_markdown/static/bootstrap_markdown/locale/bootstrap-markdown.de.js
bootstrap_markdown/static/bootstrap_markdown/locale/bootstrap-markdown.es.js
bootstrap_markdown/static/bootstrap_markdown/locale/bootstrap-markdown.fr.js
bootstrap_markdown/static/bootstrap_markdown/locale/bootstrap-markdown.ja.js
bootstrap_markdown/static/bootstrap_markdown/locale/bootstrap-markdown.kr.js
bootstrap_markdown/static/bootstrap_markdown/locale/bootstrap-markdown.nb.js
bootstrap_markdown/static/bootstrap_markdown/locale/bootstrap-markdown.nl.js
bootstrap_markdown/static/bootstrap_markdown/locale/bootstrap-markdown.pl.js
bootstrap_markdown/static/bootstrap_markdown/locale/bootstrap-markdown.ru.js
bootstrap_markdown/static/bootstrap_markdown/locale/bootstrap-markdown.sl.js
bootstrap_markdown/static/bootstrap_markdown/locale/bootstrap-markdown.sv.js
bootstrap_markdown/static/bootstrap_markdown/locale/bootstrap-markdown.tr.js
bootstrap_markdown/static/bootstrap_markdown/locale/bootstrap-markdown.ua.js
bootstrap_markdown/static/bootstrap_markdown/locale/bootstrap-markdown.zh.js
bootstrap_markdown/templates/bootstrap_markdown/base_widget.html
django_bootstrap_markdown_editor.egg-info/PKG-INFO
django_bootstrap_markdown_editor.egg-info/SOURCES.txt
django_bootstrap_markdown_editor.egg-info/dependency_links.txt
django_bootstrap_markdown_editor.egg-info/requires.txt
django_bootstrap_markdown_editor.egg-info/top_level.txt