Metadata-Version: 1.1
Name: django-bootstrap-markdown-editor
Version: 1.3
Summary: An useful editor wrapped up in bootstrap for your forms
Home-page: https://github.com/MSA-Argentina/django-bootstrap-markdown
Author: Leandro Poblet
Author-email: leandrodrhouse@gmail.com
License: BSD
Download-URL: https://github.com/MSA-Argentina/django-bootstrap-markdown/releases/tag/1.3
Keywords: django,markdown,editor
Platform: UNKNOWN
Classifier: Programming Language :: Python
Classifier: Programming Language :: Python :: 3
Classifier: Development Status :: 4 - Beta
Classifier: Environment :: Web Environment
Classifier: Intended Audience :: Developers
Classifier: Framework :: Django
Classifier: License :: OSI Approved :: BSD License
Classifier: Operating System :: OS Independent
Classifier: Topic :: Internet :: WWW/HTTP :: Site Management
Classifier: Topic :: Software Development :: Libraries :: Python Modules
Classifier: Topic :: Utilities
